python_ai_ragbot-0.1.1.dist-info/METADATA
python_ai_ragbot-0.1.1.dist-info/WHEEL
python_ai_ragbot-0.1.1.dist-info/entry_points.txt
python_ai_ragbot-0.1.1.dist-info/licenses/LICENSE
python_ai_ragbot/__init__.py
python_ai_ragbot/config/__init__.py
python_ai_ragbot/config/defaults.py
python_ai_ragbot/config/validate.py
python_ai_ragbot/http/ __init__.py
python_ai_ragbot/http/adapters.py
python_ai_ragbot/http/handlers.py
python_ai_ragbot/http/types.py
python_ai_ragbot/index.py
python_ai_ragbot/rag/__init__.py
python_ai_ragbot/rag/builder.py
python_ai_ragbot/rag/loaders.py
python_ai_ragbot/rag/query.py
python_ai_ragbot/utils/errors.py
python_ai_ragbot/voice/voice.py
python_ai_ragbot-0.1.1.dist-info/RECORD
