Metadata-Version: 2.1
Name: python-ai-ragbot
Version: 0.1.1
Summary: AI RAG bot utilities for OpenAI + LangChain with FAISS
Keywords: RAG,LangChain,OpenAI,vector search,chatbot,LLM
Author-Email: Kushal Soni <kushalsoni.dev@gmail.com>
License: MIT
Classifier: Development Status :: 3 - Alpha
Classifier: Programming Language :: Python :: 3.9
Classifier: Programming Language :: Python :: 3.10
Classifier: License :: OSI Approved :: MIT License
Classifier: Intended Audience :: Developers
Classifier: Topic :: Software Development :: Libraries
Requires-Python: >=3.9
Requires-Dist: openai>=1.107.3
Requires-Dist: langchain>=0.3.27
Requires-Dist: faiss-cpu>=1.11.0.post1
Requires-Dist: pypdf>=6.0.0
Requires-Dist: python-docx>=1.2.0
Requires-Dist: beautifulsoup4>=4.13.5
Requires-Dist: requests>=2.32.5
Requires-Dist: langchain-community>=0.3.21
Requires-Dist: langchain-openai>=0.3.33
